LICENSE
README.md
OPTIMA/__init__.py
OPTIMA/__main__.py
OPTIMA/defaults.py
OPTIMA/optima.py
OPTIMA/test.py
OPTIMA/builtin/__init__.py
OPTIMA/builtin/evaluation.py
OPTIMA/builtin/figures_of_merit.py
OPTIMA/builtin/inputs.py
OPTIMA/builtin/model.py
OPTIMA/builtin/search_space.py
OPTIMA/core/__init__.py
OPTIMA/core/evaluation.py
OPTIMA/core/inputs.py
OPTIMA/core/model.py
OPTIMA/core/search_space.py
OPTIMA/core/tools.py
OPTIMA/core/training.py
OPTIMA/core/variable_optimization.py
OPTIMA/hardware_configs/TU_Dresden.py
OPTIMA/hardware_configs/__init__.py
OPTIMA/hardware_configs/common.py
OPTIMA/hardware_configs/helpers.py
OPTIMA/helpers/__init__.py
OPTIMA/helpers/extract_data_from_NTuples.py
OPTIMA/helpers/manage_ray_nodes.py
OPTIMA/keras/__init__.py
OPTIMA/keras/model.py
OPTIMA/keras/tools.py
OPTIMA/keras/training.py
OPTIMA/lightning/__init__.py
OPTIMA/lightning/inputs.py
OPTIMA/lightning/training.py
OPTIMA/resources/__init__.py
OPTIMA/resources/config_verification.py
OPTIMA/resources/pbt_with_seed.py
optima_ml-0.4.0.dev1.dist-info/METADATA
optima_ml-0.4.0.dev1.dist-info/WHEEL
optima_ml-0.4.0.dev1.dist-info/entry_points.txt
optima_ml-0.4.0.dev1.dist-info/licenses/LICENSE
optima_ml-0.4.0.dev1.dist-info/RECORD
