Metadata-Version: 2.4
Name: optima-ml
Version: 0.4.0.dev1
Summary: Distributed hyperparameter optimization and input variable selection for artificial neural networks.
Project-URL: Homepage, https://gitlab.cern.ch/atlas-germany-dresden-vbs-group/optima
Author-email: "E. Bachmann" <erik.bachmann@tu-dresden.de>
License-Expression: GPL-3.0-only
License-File: LICENSE
Classifier: Development Status :: 3 - Alpha
Classifier: License :: OSI Approved :: GNU General Public License v3 (GPLv3)
Classifier: Operating System :: MacOS :: MacOS X
Classifier: Operating System :: POSIX :: Linux
Classifier: Programming Language :: Python
Classifier: Programming Language :: Python :: 3
Classifier: Programming Language :: Python :: 3.9
Classifier: Programming Language :: Python :: 3.10
Classifier: Programming Language :: Python :: 3.11
Classifier: Programming Language :: Python :: Implementation :: CPython
Classifier: Programming Language :: Python :: Implementation :: PyPy
Requires-Python: >=3.9.0
Requires-Dist: dill
Requires-Dist: matplotlib
Requires-Dist: multiprocess; sys_platform == 'darwin'
Requires-Dist: numpy
Requires-Dist: optuna==3.6
Requires-Dist: pandas
Requires-Dist: ray[data,train,tune]==2.11
Requires-Dist: scikit-learn
Requires-Dist: scipy
Requires-Dist: seaborn
Requires-Dist: tabulate
Provides-Extra: keras
Requires-Dist: tensorflow-macos==2.15.0; (sys_platform == 'darwin') and extra == 'keras'
Requires-Dist: tensorflow==2.15.0; (sys_platform == 'linux') and extra == 'keras'
Provides-Extra: lightning
Requires-Dist: lightning==2.1.2; extra == 'lightning'
Requires-Dist: torch==2.1.2; extra == 'lightning'
